Workbook

Sheet 01 Úvod
B2: KOFOLA ČESKOSLOVENSKO – ANALYTICKÁ PROVĚRKA 2025
B4: Podkladové výpočty ke konsolidované účetní závěrce za rok 2025
B5: Komparativní údaje za rok 2024 jsou uvedeny tam, kde jsou pro výpočty potřeba.
B7: Tento Excel obsahuje výhradně zdrojové účetní hodnoty, výpočty a kontrolní vazby.
B8: Závěry, možný dopad do účetních výkazů a návrhy kontrol jsou v samostatném memorandu (R01–R04).
B10: Účetní období: 2025 (srovnávací 2024)
B11: Jednotky: tis. Kč, pokud není uvedeno jinak
B12: Podklad: veřejné výroční zprávy Kofola ČeskoSlovensko a.s.
B14: Nezávislý studentský analytický projekt; nejedná se o statutární audit.
B17: PŘEHLED LISTŮ
B18: List | C18: Obsah
B19: 02 Výsledovka | C19: Výsledovka, vývoj tržeb, nákladů a hrubé marže
B20: 03 Segmenty | C20: Tržby a ukazatele segmentů
B21: 04 Zásoby | C21: Zásoby, opravné položky a poměrové ukazatele
B22: 05 Pohledávky | C22: Pohledávky, splatnost, opravné položky, DSO
B23: 06 Dlouhodobý majetek | C23: Přírůstky, leasing, odpisy a pozemky
B24: 07 Rozvaha a likvidita | C24: Bilanční rovnice, pracovní kapitál a likvidita
B25: 08 Peněžní toky | C25: Cash flow, FCF a dluhová služba
B26: 09 Dluh a splatnost | C26: Splatnost úvěrů, kovenanty a zadlužení
B27: 10 Souhrn propočtů | C27: Výběr vzorců pro auditní memorandum

Sheet 02 Výsledovka
B2: KONSOLIDOVANÁ VÝSLEDOVKA
B3: Ukazatel (tis. Kč) | C3: 2024 | D3: 2025 | E3: Změna | F3: Změna %
B4: Tržby | C4: 11081953 | D4: 10754328 | E4: =D4-C4 -> -327625 | F4: =IFERROR(E4/C4,0) -> -0.029563832
B5: Náklady na prodané výkony | C5: 6037140 | D5: 5675000 | E5: =D5-C5 -> -362140 | F5: =IFERROR(E5/C5,0) -> -0.059985357
B6: Hrubý zisk | C6: 5044813 | D6: 5079328 | E6: =D6-C6 -> 34515 | F6: =IFERROR(E6/C6,0) -> 0.0068416808
B7: Prodejní a distribuční náklady | C7: 3201001 | D7: 3356442 | E7: =D7-C7 -> 155441 | F7: =IFERROR(E7/C7,0) -> 0.048560122
B8: Správní náklady | C8: 705866 | D8: 606820 | E8: =D8-C8 -> -99046 | F8: =IFERROR(E8/C8,0) -> -0.14031842
B9: Provozní zisk | C9: 1243056 | D9: 1164584 | E9: =D9-C9 -> -78472 | F9: =IFERROR(E9/C9,0) -> -0.06312829
B10: Zisk před zdaněním | C10: 927301 | D10: 932910 | E10: =D10-C10 -> 5609 | F10: =IFERROR(E10/C10,0) -> 0.0060487371
B11: Čistý zisk | C11: 653152 | D11: 681589 | E11: =D11-C11 -> 28437 | F11: =IFERROR(E11/C11,0) -> 0.043538104
B14: POMĚROVÉ UKAZATELE
B15: Ukazatel | C15: 2024 | D15: 2025 | E15: Změna (p. b.)
B16: Hrubá marže | C16: =C6/C4 -> 0.45522779 | D16: =D6/D4 -> 0.47230548 | E16: =(D16-C16)*100 -> 1.7077683
B17: Podíl nákladů na prodeji | C17: =C5/C4 -> 0.54477221 | D17: =D5/D4 -> 0.52769452 | E17: =(D17-C17)*100 -> -1.7077683
B18: Provozní marže | C18: =C9/C4 -> 0.1121694 | D18: =D9/D4 -> 0.1082898 | E18: =(D18-C18)*100 -> -0.38796009
B21: NÁKLADY PODLE DRUHU
B22: Ukazatel | C22: 2024 | D22: 2025 | E22: Změna %
B23: Materiál, energie, prodané zboží | C23: 4687851 | D23: 4284321 | E23: =D23/C23-1 -> -0.086079954
B24: Osobní náklady | C24: 2340944 | D24: 2302736 | E24: =D24/C24-1 -> -0.016321621
B25: Odpisy a amortizace | C25: 674075 | D25: 760644 | E25: =D25/C25-1 -> 0.12842636
B28: Výroční zpráva Kofola 2025, konsolidovaná výsledovka B-1, náklady dle druhu B-33.

Sheet 03 Segmenty
B2: SEGMENTOVÉ TRŽBY
B3: Segment | C3: 2024 (mil. Kč) | D3: 2025 (mil. Kč) | E3: Změna (mil. Kč) | F3: Změna %
B4: CzechoSlovakia | C4: 6847.6 | D4: 6334.5 | E4: =D4-C4 -> -513.1 | F4: =D4/C4-1 -> -0.074931363
B5: Adriatic | C5: 1681.3 | D5: 1650.8 | E5: =D5-C5 -> -30.5 | F5: =D5/C5-1 -> -0.018140724
B6: Beers & Ciders | C6: 1395.9 | D6: 1440.2 | E6: =D6-C6 -> 44.3 | F6: =D6/C6-1 -> 0.031735798
B7: Fresh & Herbs | C7: 1157.2 | D7: 1328.8 | E7: =D7-C7 -> 171.6 | F7: =D7/C7-1 -> 0.14828897
B8: Celkové tržby segmentů | C8: =SUM(C4:C7) -> 11082 | D8: =SUM(D4:D7) -> 10754.3 | E8: =D8-C8 -> -327.7 | F8: =D8/C8-1 -> -0.029570475
B11: DOPLŇUJÍCÍ SEGMENTOVÉ ÚDAJE
B12: Ukazatel | C12: 2024 | D12: 2025 | E12: Změna (tis. Kč / p. b.)
B13: Adjusted EBITDA – skupina (tis. Kč) | C13: 1850994 | D13: 1816444 | E13: =D13-C13 -> -34550
B14: EBITDA – skupina (tis. Kč) | C14: 1917132 | D14: 1925228 | E14: =D14-C14 -> 8096
B15: Adjusted EBITDA marže | C15: =C13/('02 Výsledovka'!C4) -> 0.16702778 | D15: =D13/('02 Výsledovka'!D4) -> 0.16890353 | E15: =(D15-C15)*100 -> 0.18757542
B18: Výroční zpráva Kofola 2025, B-29 až B-31, A-15 až A-19

Sheet 04 Zásoby
B2: ZÁSOBY A OPRAVNÉ POLOŽKY
B3: Ukazatel (tis. Kč) | C3: 2024 | D3: 2025 | E3: Změna | F3: Změna %
B4: Zásoby brutto | C4: 974017 | D4: 1037289 | E4: =D4-C4 -> 63272 | F4: =D4/C4-1 -> 0.064959852
B5: Opravné položky | C5: 32133 | D5: 29268 | E5: =D5-C5 -> -2865 | F5: =D5/C5-1 -> -0.089160676
B6: Zásoby netto | C6: =C4-C5 -> 941884 | D6: =D4-D5 -> 1008021 | E6: =D6-C6 -> 66137 | F6: =D6/C6-1 -> 0.070217776
B9: POMĚROVÉ UKAZATELE
B10: Ukazatel | C10: 2024 | D10: 2025 | E10: Změna (p. b.)
B11: OP / hrubé zásoby | C11: =C5/C4 -> 0.032990184 | D11: =D5/D4 -> 0.028215859 | E11: =(D11-C11)*100 -> -0.47743251
B12: Zásoby / tržby | C12: =C6/'02 Výsledovka'!C4 -> 0.0849926 | D12: =D6/'02 Výsledovka'!D4 -> 0.093731659 | E12: =(D12-C12)*100 -> 0.87390584
B15: POHYB OPRAVNÝCH POLOŽEK 2025
B16: Položka | C16: 2025 (tis. Kč)
B17: Počáteční zůstatek | C17: 32133
B18: Tvorba | C18: 5888
B19: Použití / rozpuštění | C19: -8362
B20: Kurzový rozdíl | C20: -391
B21: Konečný zůstatek | C21: =SUM(C17:C20) -> 29268
B22: Kontrola proti rozvaze | C22: =C21-D5 -> 0
B25: Výroční zpráva Kofola 2025, pozn. 4.14, B-49

Sheet 05 Pohledávky
B2: OBCHODNÍ POHLEDÁVKY
B3: Ukazatel (tis. Kč) | C3: 2024 | D3: 2025 | E3: Změna | F3: Změna %
B4: Obchodní pohledávky brutto | C4: 1256656 | D4: 1139322 | E4: =D4-C4 -> -117334 | F4: =D4/C4-1 -> -0.093370023
B5: Opravné položky | C5: 41558 | D5: 38667 | E5: =D5-C5 -> -2891 | F5: =D5/C5-1 -> -0.069565427
B6: Obchodní pohledávky netto | C6: =C4-C5 -> 1215098 | D6: =D4-D5 -> 1100655 | E6: =D6-C6 -> -114443 | F6: =D6/C6-1 -> -0.094184173
B9: VĚKOVÁ STRUKTURA POHLEDÁVEK
B10: Kategorie (tis. Kč) | C10: 2024 | D10: 2025 | E10: Změna
B11: Ve splatnosti | C11: 1082066 | D11: 950386 | E11: =D11-C11 -> -131680
B12: Po splatnosti do 30 dní | C12: 105542 | D12: 96159 | E12: =D12-C12 -> -9383
B13: Po splatnosti 30–90 dní | C13: 26584 | D13: 47744 | E13: =D13-C13 -> 21160
B14: Po splatnosti 91–180 dní | C14: 7307 | D14: 12536 | E14: =D14-C14 -> 5229
B15: Po splatnosti 181–360 dní | C15: 5367 | D15: 1872 | E15: =D15-C15 -> -3495
B16: Po splatnosti více než 360 dní | C16: 29790 | D16: 30625 | E16: =D16-C16 -> 835
B17: Celkem po splatnosti | C17: =SUM(C12:C16) -> 174590 | D17: =SUM(D12:D16) -> 188936 | E17: =D17-C17 -> 14346
B18: Celkem brutto | C18: =C11+C17 -> 1256656 | D18: =D11+D17 -> 1139322 | E18: =D18-C18 -> -117334
B19: Kontrola vůči brutto | C19: =C18-C4 -> 0 | D19: =D18-D4 -> 0
B22: POMĚROVÉ UKAZATELE
B23: Ukazatel | C23: 2024 | D23: 2025 | E23: Změna (p. b.)
B24: OP / brutto | C24: =C5/C4 -> 0.033070307 | D24: =D5/D4 -> 0.033938606 | E24: =(D24-C24)*100 -> 0.086829836
B25: Po splatnosti / brutto | C25: =C17/C4 -> 0.13893221 | D25: =D17/D4 -> 0.16583196 | E25: =(D25-C25)*100 -> 2.6899746
B26: Po splatnosti do 360 dní / brutto | C26: =SUM(C12:C15)/C4 -> 0.11522644 | D26: =SUM(D12:D15)/D4 -> 0.13895194 | E26: =(D26-C26)*100 -> 2.3725496
B27: OP / pohledávky přes 90 dní | C27: =C5/SUM(C14:C16) -> 0.97866428 | D27: =D5/SUM(D14:D16) -> 0.858637 | E27: =(D27-C27)*100 -> -12.002728
B28: Pohledávky více než 90 dní | C28: =SUM(C14:C16) -> 42464 | D28: =SUM(D14:D16) -> 45033
B29: DSO – orientačně (průměr netto, dny) | D29: =AVERAGE(C6:D6)/'02 Výsledovka'!D4*365 -> 39.298125
B32: Výroční zpráva Kofola 2025, pozn. 4.15, B-49; 4.26.3, B-66

Sheet 06 Dlouhodobý majetek
B2: DLOUHODOBÝ HMOTNÝ MAJETEK
B3: Ukazatel (tis. Kč) | C3: 2024 | D3: 2025 | E3: Změna | F3: Změna %
B4: Čistá účetní hodnota DHM | C4: 4410318 | D4: 5267049 | E4: =D4-C4 -> 856731 | F4: =D4/C4-1 -> 0.19425606
B7: PŘÍRŮSTKY 2025
B8: Položka | C8: 2025 (tis. Kč)
B9: Přírůstky – additions | C9: 1173590
B10: Akvizice dceřiných společností | C10: 331278
B11: Leasingové přírůstky | C11: 224127
B12: Součet hlavních přírůstků | C12: =SUM(C9:C11) -> 1728995
B15: POZEMKY – ODPISY
B16: Ukazatel | C16: 2024 | D16: 2025
B17: Odpisy vykázané v kategorii Land (tis. Kč) | C17: 1253 | D17: 1250
B18: Oprávky – pozemky na konci roku (tis. Kč) | C18: 6326 | D18: 7526
B19: Odpisy pozemků / zisk před daní | C19: =C17/'02 Výsledovka'!C10 -> 0.0013512333 | D19: =D17/'02 Výsledovka'!D10 -> 0.0013398935
B20: Odpisy pozemků / DHM netto | C20: =C17/C4 -> 0.0002841065 | D20: =D17/D4 -> 0.00023732454
B23: Výroční zpráva Kofola 2025, pozn. 4.10, B-38 až B-41; účetní zásada „Land is not depreciated“: B-15

Sheet 07 Rozvaha a likvidita
B2: KONSOLIDOVANÁ ROZVAHA
B3: Ukazatel (tis. Kč) | C3: 2024 | D3: 2025 | E3: Změna | F3: Změna %
B4: Dlouhodobá aktiva | C4: 7246172 | D4: 8476264 | E4: =D4-C4 -> 1230092 | F4: =D4/C4-1 -> 0.16975749
B5: Oběžná aktiva | C5: 3626843 | D5: 3061941 | E5: =D5-C5 -> -564902 | F5: =D5/C5-1 -> -0.15575585
B6: Aktiva celkem | C6: =SUM(C4:C5) -> 10873015 | D6: =SUM(D4:D5) -> 11538205 | E6: =D6-C6 -> 665190 | F6: =D6/C6-1 -> 0.061178063
B7: Vlastní kapitál | C7: 2024008 | D7: 2282876 | E7: =D7-C7 -> 258868 | F7: =D7/C7-1 -> 0.1278987
B8: Dlouhodobé závazky | C8: 4739869 | D8: 5114441 | E8: =D8-C8 -> 374572 | F8: =D8/C8-1 -> 0.079025813
B9: Krátkodobé závazky | C9: 4109138 | D9: 4140888 | E9: =D9-C9 -> 31750 | F9: =D9/C9-1 -> 0.0077266814
B10: Pasiva celkem | C10: =SUM(C7:C9) -> 10873015 | D10: =SUM(D7:D9) -> 11538205 | E10: =D10-C10 -> 665190 | F10: =D10/C10-1 -> 0.061178063
B11: Bilanční rozdíl | C11: =C6-C10 -> 0 | D11: =D6-D10 -> 0
B12: Peníze a peněžní ekvivalenty | C12: 1229999 | D12: 634718 | E12: =D12-C12 -> -595281 | F12: =D12/C12-1 -> -0.48396869
B15: UKAZATELE FINANČNÍ POZICE
B16: Ukazatel | C16: 2024 | D16: 2025 | E16: Změna
B17: Podíl vlastního kapitálu na aktivech | C17: =C7/C6 -> 0.18614966 | D17: =D7/D6 -> 0.19785365 | E17: =D17-C17 -> 0.011703996
B18: Podíl dlouhodobých závazků na všech závazcích | C18: =C8/(C8+C9) -> 0.53563852 | D18: =D8/(D8+D9) -> 0.55259419 | E18: =D18-C18 -> 0.016955668
B19: Čistý pracovní kapitál | C19: =C5-C9 -> -482295 | D19: =D5-D9 -> -1078947 | E19: =D19-C19 -> -596652
B20: Běžná likvidita | C20: =C5/C9 -> 0.88262867 | D20: =D5/D9 -> 0.73944067 | E20: =D20-C20 -> -0.143188
B21: Okamžitá likvidita | C21: =C12/C9 -> 0.29933261 | D21: =D12/D9 -> 0.15328065 | E21: =D21-C21 -> -0.14605196
B22: Pohotová likvidita (bez zásob) | C22: =(C5-'04 Zásoby'!C6)/C9 -> 0.65341174 | D22: =(D5-'04 Zásoby'!D6)/D9 -> 0.49600955 | E22: =D22-C22 -> -0.15740219
B25: Výroční zpráva Kofola 2025, konsolidovaná rozvaha B-3

Sheet 08 Peněžní toky
B2: KONSOLIDOVANÉ PENĚŽNÍ TOKY
B3: Ukazatel (tis. Kč) | C3: 2024 | D3: 2025 | E3: Změna | F3: Změna %
B4: Provozní CF | C4: 1676086 | D4: 1216853 | E4: =D4-C4 -> -459233 | F4: =IFERROR(D4/C4-1,0) -> -0.27399131
B5: Investiční CF | C5: -2335818 | D5: -1872133 | E5: =D5-C5 -> 463685 | F5: =IFERROR(D5/C5-1,0) -> -0.19851076
B6: Finanční CF | C6: 809656 | D6: 79158 | E6: =D6-C6 -> -730498 | F6: =IFERROR(D6/C6-1,0) -> -0.90223255
B7: Kurzové vlivy | C7: 8976 | D7: -19159 | E7: =D7-C7 -> -28135 | F7: =IFERROR(D7/C7-1,0) -> -3.1344697
B8: Čistá změna hotovosti vč. kurzů | C8: =SUM(C4:C7) -> 158900 | D8: =SUM(D4:D7) -> -595281 | E8: =D8-C8 -> -754181
B9: Peníze na začátku období | C9: 1071099 | D9: 1229999 | E9: =D9-C9 -> 158900 | F9: =IFERROR(D9/C9-1,0) -> 0.1483523
B10: Vypočtená konečná hotovost | C10: =C9+C8 -> 1229999 | D10: =D9+D8 -> 634718
B11: Peníze na konci období | C11: 1229999 | D11: 634718 | E11: =D11-C11 -> -595281 | F11: =IFERROR(D11/C11-1,0) -> -0.48396869
B12: Kontrola hotovosti | C12: =C10-C11 -> 0 | D12: =D10-D11 -> 0
B14: Pořízení DHM a nehmotných aktiv (výdaj) | C14: 824647 | D14: 1224456 | E14: =D14-C14 -> 399809 | F14: =IFERROR(D14/C14-1,0) -> 0.48482442
B15: Akvizice dceřiných společností (výdaj) | C15: 1438403 | D15: 625726 | E15: =D15-C15 -> -812677 | F15: =IFERROR(D15/C15-1,0) -> -0.56498561
B16: Splátky bankovních úvěrů (výdaj) | C16: 317809 | D16: 508672 | E16: =D16-C16 -> 190863 | F16: =IFERROR(D16/C16-1,0) -> 0.60055883
B17: Zaplacené úroky (výdaj) | C17: 293666 | D17: 259971 | E17: =D17-C17 -> -33695 | F17: =IFERROR(D17/C17-1,0) -> -0.11473919
B18: Splátky leasingu (výdaj) | C18: 147215 | D18: 148433 | E18: =D18-C18 -> 1218 | F18: =IFERROR(D18/C18-1,0) -> 0.0082736134
B21: ODVOZENÉ UKAZATELE
B22: Ukazatel | C22: 2024 | D22: 2025 | E22: Změna
B23: FCF = CFO − výdaje na DHM a NA | C23: =C4-C14 -> 851439 | D23: =D4-D14 -> -7603 | E23: =D23-C23 -> -859042
B24: FCF po akvizicích (zjednodušeně) | C24: =C23-C15 -> -586964 | D24: =D23-D15 -> -633329 | E24: =D24-C24 -> -46365
B25: Krytí investičního CF provozním CF | C25: =C4/ABS(C5) -> 0.71755847 | D25: =D4/ABS(D5) -> 0.64998213 | E25: =D25-C25 -> -0.067576341
B26: CFO / pořízení DHM a NA | C26: =C4/C14 -> 2.0324891 | D26: =D4/D14 -> 0.99379071 | E26: =D26-C26 -> -1.0386983
B27: CAPEX / tržby | C27: =C14/'02 Výsledovka'!C4 -> 0.074413508 | D27: =D14/'02 Výsledovka'!D4 -> 0.11385704 | E27: =D27-C27 -> 0.039443536
B28: Dluhová služba (úvěry + úroky + leasing) | C28: =SUM(C16:C18) -> 758690 | D28: =SUM(D16:D18) -> 917076 | E28: =D28-C28 -> 158386
B29: Zjednodušený DSCR = CFO / dluhová služba | C29: =C4/C28 -> 2.2091843 | D29: =D4/D28 -> 1.3268835 | E29: =D29-C29 -> -0.88230077
B32: Výroční zpráva Kofola 2025, výkaz peněžních toků B-4

Sheet 09 Dluh a splatnost
B2: SMLUVNÍ TOKY Z FINANČNÍCH ZÁVAZKŮ K 31. 12. 2025
B3: Kategorie (tis. Kč) | C3: Do 3 měs. | D3: 3–12 měs. | E3: 1–2 roky | F3: 2–5 let | G3: Nad 5 let | H3: Smluvní toky | I3: Účetní hodnota
B4: Obchodní závazky | C4: 1576825 | D4: 9555 | E4: -197 | F4: 801 | G4: 12 | H4: 1586996 | I4: 1586996
B5: Bankovní úvěry | C5: 659537 | D5: 1172872 | E5: 4215445 | F5: 39568 | G5: 0 | H5: 6087422 | I5: 5577433
B6: Leasing | C6: 43287 | D6: 126639 | E6: 173834 | F6: 189949 | G6: 88652 | H6: 622361 | I6: 542644
B7: Přijaté zálohy | C7: 324057 | D7: 0 | E7: 6915 | F7: 0 | G7: 0 | H7: 330972 | I7: 330972
B8: Ostatní závazky | C8: 119525 | D8: 47122 | E8: 25462 | F8: 2942 | G8: 67068 | H8: 262119 | I8: 262119
B9: Celkem | C9: =SUM(C4:C8) -> 2723231 | D9: =SUM(D4:D8) -> 1356188 | E9: =SUM(E4:E8) -> 4421459 | F9: =SUM(F4:F8) -> 233260 | G9: =SUM(G4:G8) -> 155732 | H9: =SUM(H4:H8) -> 8889870 | I9: =SUM(I4:I8) -> 8300164
B12: SMLUVNÍ TOKY Z FINANČNÍCH ZÁVAZKŮ K 31. 12. 2024
B13: Kategorie (tis. Kč) | C13: Do 3 měs. | D13: 3–12 měs. | E13: 1–2 roky | F13: 2–5 let | G13: Nad 5 let | H13: Smluvní toky | I13: Účetní hodnota
B14: Obchodní závazky | C14: 1685099 | D14: 9909 | E14: 309 | F14: 0 | G14: 0 | H14: 1695317 | I14: 1695317
B15: Bankovní úvěry | C15: 171080 | D15: 1194010 | E15: 3957745 | F15: 48700 | G15: 0 | H15: 5371535 | I15: 4769045
B16: Leasing | C16: 30746 | D16: 98748 | E16: 125083 | F16: 175464 | G16: 88845 | H16: 518886 | I16: 414626
B17: Přijaté zálohy | C17: 308992 | D17: 0 | E17: 7335 | F17: 0 | G17: 0 | H17: 316327 | I17: 316327
B18: Ostatní závazky | C18: 103623 | D18: 149861 | E18: 52180 | F18: 8471 | G18: 161405 | H18: 475540 | I18: 475540
B19: Celkem | C19: =SUM(C14:C18) -> 2299540 | D19: =SUM(D14:D18) -> 1452528 | E19: =SUM(E14:E18) -> 4142652 | F19: =SUM(F14:F18) -> 232635 | G19: =SUM(G14:G18) -> 250250 | H19: =SUM(H14:H18) -> 8377605 | I19: =SUM(I14:I18) -> 7670855
B22: SROVNÁNÍ SPLATNOSTI A ZADLUŽENÍ
B23: Ukazatel | C23: 2024 | D23: 2025 | E23: Změna | F23: Změna %
B24: Smluvní platby úvěrů do 12 měsíců | C24: =SUM(C15:D15) -> 1365090 | D24: =SUM(C5:D5) -> 1832409 | E24: =D24-C24 -> 467319 | F24: =D24/C24-1 -> 0.34233567
B25: Smluvní platby úvěrů v pásmu 1–2 roky | C25: =E15 -> 3957745 | D25: =E5 -> 4215445 | E25: =D25-C25 -> 257700 | F25: =D25/C25-1 -> 0.065112836
B26: Bankovní úvěry – účetní hodnota | C26: =I15 -> 4769045 | D26: =I5 -> 5577433 | E26: =D26-C26 -> 808388 | F26: =D26/C26-1 -> 0.16950731
B27: Leasing – účetní hodnota | C27: =I16 -> 414626 | D27: =I6 -> 542644 | E27: =D27-C27 -> 128018 | F27: =D27/C27-1 -> 0.30875536
B28: Hotovost | C28: ='07 Rozvaha a likvidita'!C12 -> 1229999 | D28: ='07 Rozvaha a likvidita'!D12 -> 634718 | E28: =D28-C28 -> -595281 | F28: =D28/C28-1 -> -0.48396869
B29: Čistý dluh | C29: =C26+C27-C28 -> 3953672 | D29: =D26+D27-D28 -> 5485359 | E29: =D29-C29 -> 1531687 | F29: =D29/C29-1 -> 0.38740872
B30: Adjusted EBITDA | C30: 1850994 | D30: 1816444 | E30: =D30-C30 -> -34550 | F30: =D30/C30-1 -> -0.018665647
B31: Čistý dluh / adjusted EBITDA | C31: =C29/C30 -> 2.1359723 | D31: =D29/D30 -> 3.0198338 | E31: =D31-C31 -> 0.88386146
B32: Nevyčerpané úvěrové linky | C32: 318387 | D32: 66400 | E32: =D32-C32 -> -251987 | F32: =D32/C32-1 -> -0.79144877
B33: CFO / krátkodobý bankovní dluh (účetní hodnota) | C33: ='08 Peněžní toky'!C4/C34 -> 1.5562819 | D33: ='08 Peněžní toky'!D4/D34 -> 0.8043283 | E33: =D33-C33 -> -0.75195357
B34: Krátkodobé bankovní úvěry (tis. Kč) | C34: 1076981 | D34: 1512881
B36: Výroční zpráva Kofola 2025, 4.19 B-53 až B-54, 4.26.4 B-67 až B-68, 4.27 B-68
B37: Zdroj krátkodobých úvěrů: výroční zpráva 2025, konsolidovaná rozvaha B-3.
B38: Položka −197 tis. Kč je převzata z tabulky B-67; bez detailu nelze její charakter ověřit.

Sheet 10 Souhrn propočtů
B2: SOUHRN VÝPOČTŮ PRO MEMORANDUM
B3: Ukazatel | C3: 2024 | D3: 2025 | E3: Změna / rozdíl | F3: Zdrojový list
B4: Tržby | C4: ='02 Výsledovka'!C4 -> 11081953 | D4: ='02 Výsledovka'!D4 -> 10754328 | E4: ='02 Výsledovka'!E4 -> -327625 | F4: 02 Výsledovka
B5: Hrubá marže | C5: ='02 Výsledovka'!C16 -> 0.45522779 | D5: ='02 Výsledovka'!D16 -> 0.47230548 | E5: ='02 Výsledovka'!E16 -> 1.7077683 | F5: 02 Výsledovka
B6: Zásoby netto | C6: ='04 Zásoby'!C6 -> 941884 | D6: ='04 Zásoby'!D6 -> 1008021 | E6: ='04 Zásoby'!E6 -> 66137 | F6: 04 Zásoby
B7: OP / zásoby brutto | C7: ='04 Zásoby'!C11 -> 0.032990184 | D7: ='04 Zásoby'!D11 -> 0.028215859 | E7: ='04 Zásoby'!E11 -> -0.47743251 | F7: 04 Zásoby
B8: Pohledávky po splatnosti / brutto | C8: ='05 Pohledávky'!C25 -> 0.13893221 | D8: ='05 Pohledávky'!D25 -> 0.16583196 | E8: ='05 Pohledávky'!E25 -> 2.6899746 | F8: 05 Pohledávky
B9: OP / brutto pohledávky | C9: ='05 Pohledávky'!C24 -> 0.033070307 | D9: ='05 Pohledávky'!D24 -> 0.033938606 | E9: ='05 Pohledávky'!E24 -> 0.086829836 | F9: 05 Pohledávky
B10: DHM netto | C10: ='06 Dlouhodobý majetek'!C4 -> 4410318 | D10: ='06 Dlouhodobý majetek'!D4 -> 5267049 | E10: ='06 Dlouhodobý majetek'!E4 -> 856731 | F10: 06 Dlouhodobý majetek
B11: Odpisy v kategorii Land | C11: ='06 Dlouhodobý majetek'!C17 -> 1253 | D11: ='06 Dlouhodobý majetek'!D17 -> 1250 | E11: =D11-C11 -> -3 | F11: 06 Dlouhodobý majetek
B12: Běžná likvidita | C12: ='07 Rozvaha a likvidita'!C20 -> 0.88262867 | D12: ='07 Rozvaha a likvidita'!D20 -> 0.73944067 | E12: ='07 Rozvaha a likvidita'!E20 -> -0.143188 | F12: 07 Rozvaha a likvidita
B13: Pracovní kapitál | C13: ='07 Rozvaha a likvidita'!C19 -> -482295 | D13: ='07 Rozvaha a likvidita'!D19 -> -1078947 | E13: ='07 Rozvaha a likvidita'!E19 -> -596652 | F13: 07 Rozvaha a likvidita
B14: Provozní CF | C14: ='08 Peněžní toky'!C4 -> 1676086 | D14: ='08 Peněžní toky'!D4 -> 1216853 | E14: ='08 Peněžní toky'!E4 -> -459233 | F14: 08 Peněžní toky
B15: Free cash flow | C15: ='08 Peněžní toky'!C23 -> 851439 | D15: ='08 Peněžní toky'!D23 -> -7603 | E15: ='08 Peněžní toky'!E23 -> -859042 | F15: 08 Peněžní toky
B16: Zjednodušený DSCR | C16: ='08 Peněžní toky'!C29 -> 2.2091843 | D16: ='08 Peněžní toky'!D29 -> 1.3268835 | E16: ='08 Peněžní toky'!E29 -> -0.88230077 | F16: 08 Peněžní toky
B17: Úvěry splatné do 12 měs. (smluvní platby) | C17: ='09 Dluh a splatnost'!C24 -> 1365090 | D17: ='09 Dluh a splatnost'!D24 -> 1832409 | E17: ='09 Dluh a splatnost'!E24 -> 467319 | F17: 09 Dluh a splatnost
B18: Čistý dluh / adjusted EBITDA | C18: ='09 Dluh a splatnost'!C31 -> 2.1359723 | D18: ='09 Dluh a splatnost'!D31 -> 3.0198338 | E18: ='09 Dluh a splatnost'!E31 -> 0.88386146 | F18: 09 Dluh a splatnost
B22: Ukazatele vycházejí z listů 02–09; související závěry a možné účetní dopady jsou v memorandu R01–R04.
